dikshantdata/__init__.py
dikshantdata/exceptions.py
dikshantdata/generator.py
dikshantdata/schemas.py
dikshantdata-0.1.2.dist-info/licenses/LICENSE.txt
dikshantdata-0.1.2.dist-info/METADATA
dikshantdata-0.1.2.dist-info/WHEEL
dikshantdata-0.1.2.dist-info/entry_points.txt
dikshantdata-0.1.2.dist-info/top_level.txt
dikshantdata-0.1.2.dist-info/RECORD
