Metadata-Version: 2.4
Name: dikshantdata
Version: 0.1.2
Summary: Static schema-based fake data generator (Pandas output only)
Author-email: Dikshant Ghimire <dikkughimire@gmail.com>
Project-URL: Homepage, https://github.com/dikshantgh/dikshantdata
Project-URL: Repository, https://github.com/dikshantgh/dikshantdata
Project-URL: Issues, https://github.com/dikshantgh/dikshantdata/issues
Requires-Python: >=3.7
License-File: LICENSE.txt
Requires-Dist: pandas>=1.0
Dynamic: license-file
